fast_mine/__init__.py
fast_mine/core.py
fast_mine-0.1.0.dist-info/METADATA
fast_mine-0.1.0.dist-info/WHEEL
fast_mine-0.1.0.dist-info/licenses/LICENSE
fast_mine-0.1.0.dist-info/RECORD
