Metadata-Version: 2.4
Name: fast-mine
Version: 0.1.0
Summary: A Numba-accelerated Python implementation of MINE (Maximal Information-based Nonparametric Exploration) statistics.
Project-URL: Homepage, https://github.com/EichiUehara/fast-mine
Author-email: Eichi Uehara <eichi.uehara@aflo.one>
License:                     GNU GENERAL PUBLIC LICENSE
License-File: LICENSE
Keywords: correlation,mic,mine,numba,statistics
Classifier: Development Status :: 4 - Beta
Classifier: Intended Audience :: Science/Research
Classifier: License :: OSI Approved :: GNU General Public License v3 (GPLv3)
Classifier: Programming Language :: Python :: 3
Classifier: Topic :: Scientific/Engineering :: Mathematics
Requires-Python: >=3.8
Requires-Dist: numba
Requires-Dist: numpy
